requirements_magic
